{
  "videos": [
    {
      "title": "Afreen",
      "imageUrl": "https://encrypted-tbn0.gstatic.com/images?q=tbn:ANd9GcSwQ3ciZMub0-lAli7M092T3luy0GC5VKhdRA&s",
      "videoUrl": "https://www.youtube.com/embed/kw4tT7SCmaY?si=c3WLeFs1zJZB7g1h&autoplay=1",
      "id": 9
    },
    {
      "title": "Heeriye",
      "imageUrl": "https://i.ytimg.com/vi/RLzC55ai0eo/maxresdefault.jpg",
      "videoUrl": "https://www.youtube.com/embed/RLzC55ai0eo?si=c3WLeFs1zJZB7g1h&autoplay=1",
      "id": 10
    },
    {
      "title": "Illuminati",
      "imageUrl": "https://i.ytimg.com/vi/yH7eDWTH5iM/maxresdefault.jpg",
      "videoUrl": "https://www.youtube.com/embed/yH7eDWTH5iM?si=c3WLeFs1zJZB7g1h&autoplay=1",
      "id": 11
    }
  ],
  "categories": [
    {
      "category": "Movies",
      "videos": [],
      "id": 2
    },
    {
      "category": "Tutorial",
      "videos": [],
      "id": 3
    },
    {
      "category": "Music",
      "videos": [
        {
          "title": "Afreen",
          "imageUrl": "https://encrypted-tbn0.gstatic.com/images?q=tbn:ANd9GcSwQ3ciZMub0-lAli7M092T3luy0GC5VKhdRA&s",
          "videoUrl": "https://www.youtube.com/embed/kw4tT7SCmaY?si=c3WLeFs1zJZB7g1h&autoplay=1",
          "id": 9
        },
        {
          "title": "Heeriye",
          "imageUrl": "https://i.ytimg.com/vi/RLzC55ai0eo/maxresdefault.jpg",
          "videoUrl": "https://www.youtube.com/embed/RLzC55ai0eo?si=c3WLeFs1zJZB7g1h&autoplay=1",
          "id": 10
        },
        {
          "title": "Illuminati",
          "imageUrl": "https://i.ytimg.com/vi/yH7eDWTH5iM/maxresdefault.jpg",
          "videoUrl": "https://www.youtube.com/embed/yH7eDWTH5iM?si=c3WLeFs1zJZB7g1h&autoplay=1",
          "id": 11
        }
      ],
      "id": 4
    }
  ],
  "history": [
    {
      "vid": 10,
      "title": "Heeriye",
      "url": "https://www.youtube.com/embed/RLzC55ai0eo?si=c3WLeFs1zJZB7g1h&autoplay=1",
      "date": "2024-09-18T10:49:58.837Z",
      "id": 2
    },
    {
      "vid": 10,
      "title": "Heeriye",
      "url": "https://www.youtube.com/embed/RLzC55ai0eo?si=c3WLeFs1zJZB7g1h&autoplay=1",
      "date": "2024-09-18T11:05:56.765Z",
      "id": 3
    },
    {
      "vid": 10,
      "title": "Heeriye",
      "url": "https://www.youtube.com/embed/RLzC55ai0eo?si=c3WLeFs1zJZB7g1h&autoplay=1",
      "date": "2024-09-19T10:24:33.480Z",
      "id": 4
    },
    {
      "vid": 9,
      "title": "Afreen",
      "url": "https://www.youtube.com/embed/kw4tT7SCmaY?si=c3WLeFs1zJZB7g1h&autoplay=1",
      "date": "2024-09-19T11:33:13.771Z",
      "id": 5
    },
    {
      "vid": 11,
      "title": "Illuminati",
      "url": "https://www.youtube.com/embed/yH7eDWTH5iM?si=c3WLeFs1zJZB7g1h&autoplay=1",
      "date": "2024-09-19T11:33:17.774Z",
      "id": 6
    }
  ]
}